cloudlaunch_cli/__init__.py
cloudlaunch_cli/config.py
cloudlaunch_cli/main.py
cloudlaunch_cli/api/__init__.py
cloudlaunch_cli/api/client.py
cloudlaunch_cli/api/cloud_credentials.py
cloudlaunch_cli/api/endpoints.py
cloudlaunch_cli/api/resources.py
cloudlaunch_cli-0.2.1.dist-info/METADATA
cloudlaunch_cli-0.2.1.dist-info/RECORD
cloudlaunch_cli-0.2.1.dist-info/WHEEL
cloudlaunch_cli-0.2.1.dist-info/entry_points.txt
cloudlaunch_cli-0.2.1.dist-info/top_level.txt
