Metadata-Version: 2.1
Name: cloudlaunch-cli
Version: 0.2.1
Summary: Command line client to the CloudLaunch API.
Home-page: https://github.com/CloudVE/cloudlaunch_cli
Author: Galaxy and GVL Projects
Author-email: help@CloudVE.org
License: MIT license
Keywords: cloudlaunch_cli
Platform: UNKNOWN
Classifier: Development Status :: 2 - Pre-Alpha
Classifier: Intended Audience :: Developers
Classifier: License :: OSI Approved :: MIT License
Classifier: Natural Language :: English
Classifier: Programming Language :: Python :: 3
Classifier: Programming Language :: Python :: 3.6
Provides-Extra: test
Provides-Extra: dev
Requires-Dist: Click (>=6.0)
Requires-Dist: coreapi (==2.2.3)
Requires-Dist: arrow (==0.12.0)
Provides-Extra: dev
Requires-Dist: sphinx (>=1.3.1); extra == 'dev'
Requires-Dist: bumpversion (>=0.5.3); extra == 'dev'
Requires-Dist: twine; extra == 'dev'
Requires-Dist: tox (>=2.9.1); extra == 'dev'
Requires-Dist: coverage (>=4.4.1); extra == 'dev'
Requires-Dist: flake8 (>=3.4.1); extra == 'dev'
Requires-Dist: flake8-import-order (>=0.13); extra == 'dev'
Requires-Dist: Click (>=6.0); extra == 'dev'
Requires-Dist: coreapi (==2.2.3); extra == 'dev'
Requires-Dist: arrow (==0.12.0); extra == 'dev'
Provides-Extra: test
Requires-Dist: tox (>=2.9.1); extra == 'test'
Requires-Dist: coverage (>=4.4.1); extra == 'test'
Requires-Dist: flake8 (>=3.4.1); extra == 'test'
Requires-Dist: flake8-import-order (>=0.13); extra == 'test'
Requires-Dist: Click (>=6.0); extra == 'test'
Requires-Dist: coreapi (==2.2.3); extra == 'test'
Requires-Dist: arrow (==0.12.0); extra == 'test'
